mmlparser/__init__.py
mmlparser/mmlparser.py
mmlparser/examples/__init__.py
mmlparser/examples/async_player.py
mmlparser/examples/simple_player.py
mmlparser/examples/songs.py
mmlparser-0.3.0.dist-info/LICENSE
mmlparser-0.3.0.dist-info/LICENSE~
mmlparser-0.3.0.dist-info/METADATA
mmlparser-0.3.0.dist-info/WHEEL
mmlparser-0.3.0.dist-info/top_level.txt
mmlparser-0.3.0.dist-info/RECORD
