Metadata-Version: 2.1
Name: mmlparser
Version: 0.3.0
Summary: MML (Music Macro Language) parser and player for Python
Home-page: https://gitlab.com/cjaikaeo/mmlparser-python
Author: Chaiporn Jaikaeo
Author-email: chaiporn.j@ku.ac.th
License: UNKNOWN
Platform: UNKNOWN
Classifier: Programming Language :: Python :: 3
Classifier: License :: OSI Approved :: BSD License
Classifier: Operating System :: OS Independent
Classifier: Topic :: Multimedia :: Sound/Audio
